pygamecontroller/__init__.py
pygame_controller-0.2.0.dist-info/LICENSE
pygame_controller-0.2.0.dist-info/METADATA
pygame_controller-0.2.0.dist-info/WHEEL
pygame_controller-0.2.0.dist-info/top_level.txt
pygame_controller-0.2.0.dist-info/RECORD
