Metadata-Version: 2.1
Name: pygame-controller
Version: 0.2.0
Summary: Helper class to interface robots to game controllers on the Raspberry Pi.
Home-page: https://github.com/Footleg/pygame-controller
Author: Paul 'Footleg' Fretwell
Author-email: drfootleg@gmail.com
Project-URL: Bug Tracker, https://github.com/Footleg/pygame-controller/issues
Classifier: Development Status :: 5 - Production/Stable
Classifier: Programming Language :: Python :: 3
Classifier: License :: OSI Approved :: GNU General Public License v3 or later (GPLv3+)
Classifier: Operating System :: OS Independent
Requires-Python: >=3.6
License-File: LICENSE
Requires-Dist: pygame (>=1.9)
